{
    "sku": "MEDIA-003",
    "category": "music",
    "locales": {
        "en_US": {
            "name": "Spotify Premium Family Plan",
            "description": "Music streaming service for up to 6 family members. Ad-free listening with offline downloads and high-quality audio."
        },
        "de_DE": {
            "name": "Spotify Premium Familienabo",
            "description": "Musik-Streaming-Service für bis zu 6 Familienmitglieder. Werbefreies Hören mit Offline-Downloads und hochwertiger Audioqualität."
        }
    }
}